tk_tools/__init__.py
tk_tools/canvas.py
tk_tools/groups.py
tk_tools/images.py
tk_tools/tooltips.py
tk_tools/version.py
tk_tools/widgets.py
tk_tools-0.12.0.dist-info/METADATA
tk_tools-0.12.0.dist-info/WHEEL
tk_tools-0.12.0.dist-info/top_level.txt
tk_tools-0.12.0.dist-info/zip-safe
tk_tools-0.12.0.dist-info/RECORD
