Metadata-Version: 2.1
Name: tk-tools
Version: 0.12.0
Summary: Tkinter-native toolset and widget library
Home-page: https://github.com/slightlynybbled/tk_tools
Author: Jason R. Jones
Author-email: slightlynybbled@gmail.com
License: MIT
Keywords: tkinter gui widgets
Platform: UNKNOWN
Classifier: Development Status :: 4 - Beta
Classifier: Programming Language :: Python :: 3
Classifier: Programming Language :: Python :: 3.5
Classifier: Programming Language :: Python :: 3.6
Classifier: Programming Language :: Python :: 3.7
Classifier: Natural Language :: English
Requires-Dist: engineering-notation (>=0.5)
